schematic/state_machine/verilog/state_machine.v
module state_machine(
    input clk,
    input rst_z,
    input start,
    input single_ended,
    input en_offset_cal,
    input comp_p,
    input vin_p_sw_on,
    input vin_n_sw_on,
    input en_vcm_sw_o_i,
    input [10:0] vcm_o_i,

    output [5:0] data,
    output clk_data,
    output sample_o,
    output reg [10:0] vcm_o,
    output reg [10:0] vref_z_p_o,
    output reg [10:0] vref_z_n_o,
    output reg [10:0] vss_p_o,
    output reg [10:0] vss_n_o,
    output reg vcm_dummy_o,
    output reg en_vcm_sw_o,
    output reg en_comp,
    output reg offset_cal_cycle,
    output reg en_offset_cal_o
);

    // =====================================================
    // INTERNAL DECLARATIONS (REQUIRED FOR IVERILOG)
    // =====================================================

    reg [1:0] state;
    parameter idle = 2'd0, sample = 2'd1, convert = 2'd2;

    reg counter_sample;
    reg single_ended_reg;
    reg [11:0] counter;
    reg [11:0] result;

    reg allow_vcm_sw;
    reg [10:0] allow_vref_sw;

    integer i;
    wire [11:0] en_dac_out;

    // =====================================================
    // FSM
    // =====================================================

    always @(posedge clk or negedge rst_z) begin
        if (!rst_z)
            state <= idle;
        else case (state)
            idle:    state <= start ? sample : idle;
            sample:  state <= counter_sample ? convert : sample;
            convert: state <= ((counter == 12'hFFF && ~single_ended_reg) ||
                               (counter == 12'hFFE &&  single_ended_reg)) ? idle : convert;
            default: state <= idle;
        endcase
    end

    // =====================================================
    // SAMPLE COUNTER
    // =====================================================

    always @(posedge clk or negedge rst_z) begin
        if (!rst_z)
            counter_sample <= 1'b0;
        else if (state != sample)
            counter_sample <= 1'b0;
        else
            counter_sample <= ~counter_sample;
    end

    // =====================================================
    // LATCH SINGLE ENDED
    // =====================================================

    always @(posedge clk or negedge rst_z) begin
        if (!rst_z)
            single_ended_reg <= 1'b0;
        else if (state == idle)
            single_ended_reg <= single_ended;
    end

    // =====================================================
    // SAR COUNTER
    // =====================================================

    always @(posedge clk or negedge rst_z) begin
        if (!rst_z)
            counter <= 12'b0;
        else if (state == idle || state == sample)
            counter <= 12'b0;
        else if (state == convert) begin
            counter <= counter >> 1;
            counter[11] <= 1'b1;
        end
    end

    assign en_dac_out = (~counter) & (12'h800 + (counter >> 1));

    // =====================================================
    // SAR RESULT
    // =====================================================

    always @(posedge clk or negedge rst_z) begin
        if (!rst_z)
            result <= 12'd0;
        else if (state == sample)
            result <= 12'd0;
        else if (state == convert) begin
            if (single_ended_reg) begin
                for (i = 0; i < 11; i = i + 1)
                    result[i] <= en_dac_out[i+1] ? comp_p : result[i];
                result[11] <= 1'b0;
            end else begin
                for (i = 0; i < 12; i = i + 1)
                    result[i] <= en_dac_out[i] ? comp_p : result[i];
            end
        end
    end

    // =====================================================
    // OUTPUT LOGIC
    // =====================================================

    assign sample_o = ((state == sample) | en_vcm_sw_o_i) & ~counter[11] & (state != idle);
    assign clk_data = counter[5] & (state == convert);
    assign data     = counter[4] ? ~result[5:0]
                                 : {~(result[11] | single_ended_reg), ~result[10:6]};

    always @(*) begin
        en_offset_cal_o = rst_z & en_offset_cal;
        allow_vcm_sw    = ~(vin_p_sw_on | vin_n_sw_on);
        vcm_dummy_o     = (state == convert) & allow_vcm_sw;

        if (single_ended_reg) begin
            en_comp          = ~clk & (state == convert) & ~(~en_offset_cal & counter[1]);
            offset_cal_cycle = counter[1] & en_offset_cal;
            vcm_o            = 11'd0;
            vref_z_p_o       = result[10:0] | (~allow_vref_sw);
            vref_z_n_o       = 11'h7FF;
            vss_p_o          = (result[10:0] | (~allow_vref_sw)) & {11{(state==convert)&allow_vcm_sw}};
            vss_n_o          = {11{(state==convert)&allow_vcm_sw}};
            en_vcm_sw_o      = (counter[1] & (state==convert)) | (state==sample);
            allow_vref_sw    = {11{(state==convert)&allow_vcm_sw}} & {1'b1,counter[11:2]};
        end else begin
            en_comp          = ~clk & (state == convert) & ~(~en_offset_cal & counter[0]);
            offset_cal_cycle = counter[0] & en_offset_cal;
            vcm_o            = ~(counter[11:1] | {11{~((state==convert)&allow_vcm_sw)}});
            vref_z_p_o       = result[11:1] | (~allow_vref_sw);
            vref_z_n_o       = (~result[11:1]) | (~allow_vref_sw);
            vss_p_o          = result[11:1] & allow_vref_sw;
            vss_n_o          = (~result[11:1]) & allow_vref_sw;
            en_vcm_sw_o      = (counter[0] & (state==convert)) | (state==sample);
            allow_vref_sw    = (~vcm_o_i) & counter[11:1];
        end
    end

endmodule

schematic/state_machine/verilog/state_machine_tb.v
`timescale 1ns/1ps
// ============================================================
// Testbench for state_machine
// IHP Analog Academy style
// Purpose: verify SAR FSM behavior (digital-only)
// ============================================================

module state_machine_tb;

  // ----------------------------------------------------------
  // Inputs to DUT
  // ----------------------------------------------------------
  reg clk;
  reg rst_z;
  reg start;
  reg single_ended;
  reg en_offset_cal;
  reg comp_p;
  reg vin_p_sw_on;
  reg vin_n_sw_on;

  // ----------------------------------------------------------
  // Outputs from DUT
  // ----------------------------------------------------------
  wire [5:0] data;
  wire       clk_data;
  wire       sample_o;

  wire [10:0] vcm;
  wire [10:0] vref_z_p;
  wire [10:0] vref_z_n;
  wire [10:0] vss_p;
  wire [10:0] vss_n;

  wire vcm_dummy;
  wire en_vcm_sw;
  wire en_comp;
  wire offset_cal_cycle;
  wire en_offset_cal_o;

  // ----------------------------------------------------------
  // Internal feedback (as in real SAR)
  // ----------------------------------------------------------
  wire        en_vcm_sw_i;
  wire [10:0] vcm_i;

  assign en_vcm_sw_i = en_vcm_sw;
  assign vcm_i       = vcm;

  // ----------------------------------------------------------
  // DUT instantiation
  // ----------------------------------------------------------
  state_machine dut (
    .clk(clk),
    .rst_z(rst_z),
    .start(start),
    .single_ended(single_ended),
    .en_offset_cal(en_offset_cal),
    .comp_p(comp_p),
    .vin_p_sw_on(vin_p_sw_on),
    .vin_n_sw_on(vin_n_sw_on),
    .en_vcm_sw_o_i(en_vcm_sw_i),
    .vcm_o_i(vcm_i),
    .data(data),
    .clk_data(clk_data),
    .sample_o(sample_o),
    .vcm_o(vcm),
    .vref_z_p_o(vref_z_p),
    .vref_z_n_o(vref_z_n),
    .vss_p_o(vss_p),
    .vss_n_o(vss_n),
    .vcm_dummy_o(vcm_dummy),
    .en_vcm_sw_o(en_vcm_sw),
    .en_comp(en_comp),
    .offset_cal_cycle(offset_cal_cycle),
    .en_offset_cal_o(en_offset_cal_o)
  );

  // ----------------------------------------------------------
  // Clock generation (50 MHz)
  // ----------------------------------------------------------
  initial clk = 1'b0;
  always #10 clk = ~clk;

  // ----------------------------------------------------------
  // Fake comparator model (VERY IMPORTANT)
  // ----------------------------------------------------------
  // This emulates an analog comparator decision
  // so that SAR FSM actually progresses.
  always @(posedge clk or negedge rst_z) begin
    if (!rst_z)
      comp_p <= 1'b0;
    else if (en_comp)
      comp_p <= ~comp_p;   // toggle decision
  end

  // ----------------------------------------------------------
  // Test sequence
  // ----------------------------------------------------------
  initial begin
    // Dump waves
    $dumpfile("state_machine.vcd");
    $dumpvars(0, state_machine_tb);

    // ----------------------
    // Initial conditions
    // ----------------------
    rst_z          = 1'b0;
    start          = 1'b0;
    single_ended   = 1'b0;
    en_offset_cal  = 1'b1;
    vin_p_sw_on    = 1'b0;
    vin_n_sw_on    = 1'b0;
    comp_p         = 1'b0;

    // ----------------------
    // Release reset
    // ----------------------
    #100;
    rst_z = 1'b1;

    // ----------------------
    // Differential conversion
    // ----------------------
    #100;
    start = 1'b1;
    #40;
    start = 1'b0;

    // Wait for conversion
    #1500;

    // ----------------------
    // Single-ended conversion
    // ----------------------
    single_ended = 1'b1;

    #100;
    start = 1'b1;
    #40;
    start = 1'b0;

    // Wait
    #1500;

    // ----------------------
    // End simulation
    // ----------------------
    $finish;
  end

endmodule

schematic/state_machine/verilog/state_machine.vcd
$date
	Wed Jan 28 00:17:11 2026
$end
$version
	Icarus Verilog
$end
$timescale
	1ps
$end
$scope module state_machine_tb $end
$var wire 1 ! en_vcm_sw_i $end
$var wire 11 " vcm_i [10:0] $end
$var wire 11 # vss_p [10:0] $end
$var wire 11 $ vss_n [10:0] $end
$var wire 11 % vref_z_p [10:0] $end
$var wire 11 & vref_z_n [10:0] $end
$var wire 1 ' vcm_dummy $end
$var wire 11 ( vcm [10:0] $end
$var wire 1 ) sample_o $end
$var wire 1 * offset_cal_cycle $end
$var wire 1 + en_vcm_sw $end
$var wire 1 , en_offset_cal_o $end
$var wire 1 - en_comp $end
$var wire 6 . data [5:0] $end
$var wire 1 / clk_data $end
$var reg 1 0 clk $end
$var reg 1 1 comp_p $end
$var reg 1 2 en_offset_cal $end
$var reg 1 3 rst_z $end
$var reg 1 4 single_ended $end
$var reg 1 5 start $end
$var reg 1 6 vin_n_sw_on $end
$var reg 1 7 vin_p_sw_on $end
$scope module dut $end
$var wire 1 0 clk $end
$var wire 1 / clk_data $end
$var wire 1 1 comp_p $end
$var wire 12 8 en_dac_out [11:0] $end
$var wire 1 2 en_offset_cal $end
$var wire 1 ! en_vcm_sw_o_i $end
$var wire 1 3 rst_z $end
$var wire 1 ) sample_o $end
$var wire 1 4 single_ended $end
$var wire 1 5 start $end
$var wire 11 9 vcm_o_i [10:0] $end
$var wire 1 6 vin_n_sw_on $end
$var wire 1 7 vin_p_sw_on $end
$var wire 6 : data [5:0] $end
$var parameter 2 ; convert $end
$var parameter 2 < idle $end
$var parameter 2 = sample $end
$var reg 1 > allow_vcm_sw $end
$var reg 11 ? allow_vref_sw [10:0] $end
$var reg 12 @ counter [11:0] $end
$var reg 1 A counter_sample $end
$var reg 1 - en_comp $end
$var reg 1 , en_offset_cal_o $end
$var reg 1 + en_vcm_sw_o $end
$var reg 1 * offset_cal_cycle $end
$var reg 12 B result [11:0] $end
$var reg 1 C single_ended_reg $end
$var reg 2 D state [1:0] $end
$var reg 1 ' vcm_dummy_o $end
$var reg 11 E vcm_o [10:0] $end
$var reg 11 F vref_z_n_o [10:0] $end
$var reg 11 G vref_z_p_o [10:0] $end
$var reg 11 H vss_n_o [10:0] $end
$var reg 11 I vss_p_o [10:0] $end
$var integer 32 J i [31:0] $end
$upscope $end
$upscope $end
$enddefinitions $end
$comment Show the parameter values. $end
$dumpall
b1 =
b0 <
b10 ;
$end
#0
$dumpvars
bx J
b0 I
bx H
bx G
b11111111111 F
b0 E
b0 D
0C
b0 B
0A
b0 @
b0 ?
1>
b111111 :
b0 9
b100000000000 8
07
06
05
04
03
12
01
00
0/
b111111 .
0-
0,
0+
0*
0)
b0 (
0'
b11111111111 &
bx %
bx $
b0 #
b0 "
0!
$end
#10000
b0 $
b0 H
b11111111111 %
b11111111111 G
10
#20000
00
#30000
10
#40000
00
#50000
10
#60000
00
#70000
10
#80000
00
#90000
10
#100000
1,
00
13
#110000
10
#120000
00
#130000
10
#140000
00
#150000
10
#160000
00
#170000
10
#180000
00
#190000
10
#200000
00
15
#210000
1)
1!
1+
b1 D
10
#220000
00
#230000
1A
10
#240000
00
05
#250000
0)
0!
0+
b11111111111 "
b11111111111 9
b11111111111 (
b11111111111 E
1'
0A
b10 D
10
#260000
1-
00
#270000
b10000000000 8
b10000000000 ?
b1111111111 "
b1111111111 9
b1111111111 (
b1111111111 E
b100000000000 @
11
0-
b1100 J
10
#280000
b10000000000 $
b10000000000 H
b1111111111 %
b1111111111 G
1-
00
#290000
b101111 .
b101111 :
b1000000000 8
b11000000000 ?
b111111111 "
b111111111 9
b111111111 (
b111111111 E
01
b10000000000 B
b110000000000 @
0-
b1100 J
10
#300000
b1000000000 #
b1000000000 I
b10111111111 &
b10111111111 F
1-
00
#310000
b100000000 8
b11100000000 ?
b11111111 "
b11111111 9
b11111111 (
b11111111 E
b111000000000 @
11
0-
b1100 J
10
#320000
b10100000000 $
b10100000000 H
b1011111111 %
b1011111111 G
1-
00
#330000
b101011 .
b101011 :
b10000000 8
b11110000000 ?
b1111111 "
b1111111 9
b1111111 (
b1111111 E
01
b10100000000 B
b111100000000 @
0-
b1100 J
10
#340000
b1010000000 #
b1010000000 I
b10101111111 &
b10101111111 F
1-
00
#350000
b1000000 8
b11111000000 ?
b111111 "
b111111 9
b111111 (
b111111 E
b111110000000 @
11
0-
b1100 J
10
#360000
b10101000000 $
b10101000000 H
b1010111111 %
b1010111111 G
1-
00
#370000
b101010 .
b101010 :
b100000 8
b11111100000 ?
b11111 "
b11111 9
b11111 (
b11111 E
01
b10101000000 B
b111111000000 @
0-
b1100 J
10
#380000
b1010100000 #
b1010100000 I
b10101011111 &
b10101011111 F
1-
00
#390000
1/
b10000 8
b11111110000 ?
b1111 "
b1111 9
b1111 (
b1111 E
b111111100000 @
11
0-
b1100 J
10
#400000
b10101010000 $
b10101010000 H
b1010101111 %
b1010101111 G
1-
00
#410000
b101111 .
b101111 :
b1000 8
b11111111000 ?
b111 "
b111 9
b111 (
b111 E
01
b10101010000 B
b111111110000 @
0-
b1100 J
10
#420000
b1010101000 #
b1010101000 I
b10101010111 &
b10101010111 F
1-
00
#430000
b100 8
b11111111100 ?
b11 "
b11 9
b11 (
b11 E
b111111111000 @
11
0-
b1100 J
10
#440000
b10101010100 $
b10101010100 H
b1010101011 %
b1010101011 G
1-
00
#450000
b101011 .
b101011 :
b10 8
b11111111110 ?
b1 "
b1 9
b1 (
b1 E
01
b10101010100 B
b111111111100 @
0-
b1100 J
10
#460000
b1010101010 #
b1010101010 I
b10101010101 &
b10101010101 F
1-
00
#470000
b1 8
b11111111111 ?
b0 "
b0 9
b0 (
b0 E
b111111111110 @
11
0-
b1100 J
10
#480000
b10101010101 $
b10101010101 H
b1010101010 %
b1010101010 G
1-
00
#490000
b101010 .
b101010 :
b0 8
1!
1+
1*
01
b10101010101 B
b111111111111 @
0-
b1100 J
10
#500000
1-
00
#510000
0/
0!
0+
0'
b0 D
b111111111111 @
11
0-
b1100 J
10
#520000
00
#530000
b100000000000 8
b0 ?
0*
b0 @
10
#540000
b0 $
b0 H
b0 #
b0 I
b11111111111 &
b11111111111 F
b11111111111 %
b11111111111 G
00
